sphere_engine/__init__.py
sphere_engine/api.py
sphere_engine/api_client.py
sphere_engine/exceptions.py
sphere_engine/apis/__init__.py
sphere_engine/apis/base.py
sphere_engine/apis/compilers.py
sphere_engine/apis/compilersV4.py
sphere_engine/apis/problems.py
sphere_engine/apis/problemsV4.py
test/__init__.py
test/test_commons.py
test/test_compilers.py
test/test_compilersV3.py
test/test_compilersV4.py
test/test_problems.py
test/test_problemsV3.py
test/test_problemsV4.py
sphere_engine-0.27.dist-info/METADATA
sphere_engine-0.27.dist-info/WHEEL
sphere_engine-0.27.dist-info/top_level.txt
sphere_engine-0.27.dist-info/RECORD
