Metadata-Version: 2.1
Name: sphere-engine
Version: 0.27
Summary: Sphere Engine SDK
Home-page: https://github.com/sphere-engine/python-client
Author: Michal Koperkiewicz, Robert Lewon
Author-email: contact@sphere-research.com
License: UNKNOWN
Download-URL: https://github.com/sphere-engine/python-client/archive/master.zip
Keywords: Sphere Research Labs,Sphere Engine,Online Compiler,Problems,Online Judge,api,sdk,online compiler,spoj,ideone
Platform: UNKNOWN
Requires-Dist: urllib3 (>=1.10)
Requires-Dist: six (>=1.9)
Requires-Dist: certifi
Requires-Dist: python-dateutil
Requires-Dist: requests
